efs/__init__.py
efs/eatfirst_osfs.py
efs/eatfirst_s3.py
efs/filesystem.py
efs-0.2.0.dist-info/DESCRIPTION.rst
efs-0.2.0.dist-info/METADATA
efs-0.2.0.dist-info/RECORD
efs-0.2.0.dist-info/WHEEL
efs-0.2.0.dist-info/metadata.json
efs-0.2.0.dist-info/top_level.txt
