Metadata-Version: 2.0
Name: efs
Version: 0.2.0
Summary: A simple wrapper around fs to work with flask and switch between local and s3fs
Home-page: https://github.com/eatfirst/python-efs
Author: EatFirst
Author-email: it+opensource@eatfirst.com
License: MIT license
Platform: UNKNOWN
Classifier: Development Status :: 5 - Production/Stable
Classifier: Intended Audience :: Developers
Classifier: License :: OSI Approved :: MIT License
Classifier: Operating System :: Unix
Classifier: Operating System :: POSIX
Classifier: Operating System :: Microsoft :: Windows
Classifier: Programming Language :: Python
Classifier: Programming Language :: Python :: 2.7
Classifier: Programming Language :: Python :: 3
Classifier: Programming Language :: Python :: 3.3
Classifier: Programming Language :: Python :: 3.4
Classifier: Programming Language :: Python :: 3.5
Classifier: Programming Language :: Python :: 3.6
Classifier: Programming Language :: Python :: Implementation :: CPython
Classifier: Programming Language :: Python :: Implementation :: PyPy
Classifier: Topic :: Utilities
Requires-Dist: Flask
Requires-Dist: fs (<3.0,>=2.0)
Requires-Dist: fs-s3fs (<2.0,>=1.0)
Requires-Dist: autorepr
